repo2text/__init__.py
repo2text/repo2text.py
repo2text-0.1.1.dist-info/LICENSE
repo2text-0.1.1.dist-info/METADATA
repo2text-0.1.1.dist-info/WHEEL
repo2text-0.1.1.dist-info/entry_points.txt
repo2text-0.1.1.dist-info/top_level.txt
repo2text-0.1.1.dist-info/RECORD
