Metadata-Version: 2.1
Name: repo2text
Version: 0.1.1
Summary: A simple utility to convert repository files to text including specific file extensions
Home-page: https://github.com/YashJain14/repo2text
Author: Yash Jain
Classifier: Programming Language :: Python :: 3
Classifier: License :: OSI Approved :: MIT License
Classifier: Operating System :: OS Independent
Requires-Python: >=3.6
License-File: LICENSE
Requires-Dist: gitpython >=3.1.0
